trlib/__init__.py
trlib/ipconstants.py
trlib/result.py
trlib/parser/__init__.py
trlib/parser/badsession.py
trlib/parser/request.py
trlib/parser/response.py
trlib/parser/session.py
trlib/parser/sessionGenerator.py
trlib/parser/sessionvalidation.py
trlib/parser/svUtils.py
trlib/parser/transaction.py
trlib-1.0.1.dist-info/LICENSE
trlib-1.0.1.dist-info/METADATA
trlib-1.0.1.dist-info/NOTICE
trlib-1.0.1.dist-info/WHEEL
trlib-1.0.1.dist-info/top_level.txt
trlib-1.0.1.dist-info/RECORD
